sinsy_cli/__init__.py
sinsy_cli/sinsy_cli.py
sinsy_cli-0.5.0.dist-info/DESCRIPTION.rst
sinsy_cli-0.5.0.dist-info/METADATA
sinsy_cli-0.5.0.dist-info/RECORD
sinsy_cli-0.5.0.dist-info/WHEEL
sinsy_cli-0.5.0.dist-info/entry_points.txt
sinsy_cli-0.5.0.dist-info/metadata.json
sinsy_cli-0.5.0.dist-info/top_level.txt
