Metadata-Version: 2.0
Name: sinsy-cli
Version: 0.5.0
Summary: Sinsy Command Line Utility
Home-page: https://gitlab.com/zeograd/sinsy-cli
Author: Olivier Jolly
Author-email: olivier@pcedev.com
License: GPLv3+
Keywords: sinsy vocal synthesis song
Platform: UNKNOWN
Classifier: Development Status :: 3 - Alpha
Classifier: Environment :: Console
Classifier: Intended Audience :: Developers
Classifier: Intended Audience :: End Users/Desktop
Classifier: Topic :: Multimedia :: Sound/Audio
Classifier: Topic :: Software Development :: Libraries :: Python Modules
Classifier: License :: OSI Approved :: GNU General Public License v3 or later (GPLv3+)
Classifier: Programming Language :: Python :: 2
Classifier: Programming Language :: Python :: 2.7
Classifier: Programming Language :: Python :: 3
Classifier: Programming Language :: Python :: 3.2
Classifier: Programming Language :: Python :: 3.3
Classifier: Programming Language :: Python :: 3.4
Classifier: Programming Language :: Python :: 3.5
Classifier: Operating System :: OS Independent
Requires-Dist: beautifulsoup4
Requires-Dist: requests
Provides-Extra: dev
Requires-Dist: check-manifest; extra == 'dev'
Requires-Dist: pylint; extra == 'dev'
Provides-Extra: test
Requires-Dist: nose2; extra == 'test'
